vhdl/paraMAC.vhd
library IEEE;
use IEEE.STD_LOGIC_1164.ALL;
use IEEE.NUMERIC_STD.ALL;

entity paraMAC is
    generic (
        N : integer := 8
    );
    port (
        clk : in std_logic;
        rst : in std_logic;
        a   : in std_logic_vector(N-1 downto 0);
        b   : in std_logic_vector(N-1 downto 0);
        res : out std_logic_vector(31 downto 0)
        );

end entity;

architecture rtl of paraMAC is

    signal acc_reg : signed(31 downto 0) := (others => '0');

begin
    process(clk, rst)
    begin
        if rst = '1' then
            acc_reg <= (others => '0');
        elsif rising_edge(clk) then
            acc_reg <= acc_reg + (signed(a) * signed(b));
        end if;

    end process;

    res <= std_logic_vector(acc_reg);

end architecture;

vhdl/tb_paraMAC.vhd
library IEEE;
use IEEE.std_logic_1164.ALL;
use IEEE.numeric_std.ALL;

entity tb_paraMAC is
end entity;

architecture sim of tb_paraMAC is

    constant N : integer := 8;

    signal clk : std_logic := '0';
    signal rst : std_logic := '1';
    signal a   : std_logic_vector(N-1 downto 0) := (others => '0');
    signal b   : std_logic_vector(N-1 downto 0) := (others => '0');
    signal res : std_logic_vector(31 downto 0);

    constant clk_period : time := 10 ns;

begin

    -- 1) Clock
    clk_process : process
    begin
        while true loop
            clk <= '0';
            wait for clk_period/2;
            clk <= '1';
            wait for clk_period/2;
        end loop;
    end process clk_process;

    -- 2) DUT
    uut : entity work.paraMAC
        generic map ( N => N )
        port map (
            clk => clk,
            rst => rst,
            a   => a,
            b   => b,
            res => res
        );

    -- 3) Stimulus
    stim_proc : process
    begin
        -- Reset
        rst <= '1';
        wait for 3*clk_period;
        rst <= '0';

        -- First test
        a <= std_logic_vector(to_unsigned(2, N));
        b <= std_logic_vector(to_unsigned(3, N));
        wait for 5*clk_period;

        -- Second test
        a <= std_logic_vector(to_unsigned(4, N));
        b <= std_logic_vector(to_unsigned(5, N));
        wait for 5*clk_period;

        -- Third test
        a <= std_logic_vector(to_unsigned(7, N));
        b <= std_logic_vector(to_unsigned(1, N));
        wait for 5*clk_period;

        -- Stop
        wait;
    end process stim_proc;

end architecture sim;

vhdl/paraMAC.vcd
$date
  Fri Oct  3 18:49:58 2025
$end
$version
  GHDL v0
$end
$timescale
  1 fs
$end
$scope module standard $end
$upscope $end
$scope module std_logic_1164 $end
$upscope $end
$scope module numeric_std $end
$upscope $end
$scope module tb_paramac $end
$var reg 1 ! clk $end
$var reg 1 " rst $end
$var reg 8 # a[7:0] $end
$var reg 8 $ b[7:0] $end
$var reg 32 % res[31:0] $end
$scope module uut $end
$var reg 1 & clk $end
$var reg 1 ' rst $end
$var reg 8 ( a[7:0] $end
$var reg 8 ) b[7:0] $end
$var reg 32 * res[31:0] $end
$var reg 32 + acc_reg[31:0] $end
$upscope $end
$upscope $end
$enddefinitions $end
#0
0!
1"
b00000000 #
b00000000 $
b00000000000000000000000000000000 %
0&
1'
b00000000 (
b00000000 )
b00000000000000000000000000000000 *
b00000000000000000000000000000000 +
#5000000
1!
1&
#10000000
0!
0&
#15000000
1!
1&
#20000000
0!
0&
#25000000
1!
1&
#30000000
0!
0"
b00000010 #
b00000011 $
0&
0'
b00000010 (
b00000011 )
#35000000
1!
b00000000000000000000000000000110 %
1&
b00000000000000000000000000000110 *
b00000000000000000000000000000110 +
#40000000
0!
0&
#45000000
1!
b00000000000000000000000000001100 %
1&
b00000000000000000000000000001100 *
b00000000000000000000000000001100 +
#50000000
0!
0&
#55000000
1!
b00000000000000000000000000010010 %
1&
b00000000000000000000000000010010 *
b00000000000000000000000000010010 +
#60000000
0!
0&
#65000000
1!
b00000000000000000000000000011000 %
1&
b00000000000000000000000000011000 *
b00000000000000000000000000011000 +
#70000000
0!
0&
#75000000
1!
b00000000000000000000000000011110 %
1&
b00000000000000000000000000011110 *
b00000000000000000000000000011110 +
#80000000
0!
b00000100 #
b00000101 $
0&
b00000100 (
b00000101 )
#85000000
1!
b00000000000000000000000000110010 %
1&
b00000000000000000000000000110010 *
b00000000000000000000000000110010 +
#90000000
0!
0&
#95000000
1!
b00000000000000000000000001000110 %
1&
b00000000000000000000000001000110 *
b00000000000000000000000001000110 +
#100000000
0!
0&
#105000000
1!
b00000000000000000000000001011010 %
1&
b00000000000000000000000001011010 *
b00000000000000000000000001011010 +
#110000000
0!
0&
#115000000
1!
b00000000000000000000000001101110 %
1&
b00000000000000000000000001101110 *
b00000000000000000000000001101110 +
#120000000
0!
0&
#125000000
1!
b00000000000000000000000010000010 %
1&
b00000000000000000000000010000010 *
b00000000000000000000000010000010 +
#130000000
0!
b00000111 #
b00000001 $
0&
b00000111 (
b00000001 )
#135000000
1!
b00000000000000000000000010001001 %
1&
b00000000000000000000000010001001 *
b00000000000000000000000010001001 +
#140000000
0!
0&
#145000000
1!
b00000000000000000000000010010000 %
1&
b00000000000000000000000010010000 *
b00000000000000000000000010010000 +
#150000000
0!
0&
#155000000
1!
b00000000000000000000000010010111 %
1&
b00000000000000000000000010010111 *
b00000000000000000000000010010111 +
#160000000
0!
0&
#165000000
1!
b00000000000000000000000010011110 %
1&
b00000000000000000000000010011110 *
b00000000000000000000000010011110 +
#170000000
0!
0&
#175000000
1!
b00000000000000000000000010100101 %
1&
b00000000000000000000000010100101 *
b00000000000000000000000010100101 +
#180000000
0!
0&
#185000000
1!
b00000000000000000000000010101100 %
1&
b00000000000000000000000010101100 *
b00000000000000000000000010101100 +
#190000000
0!
0&
#195000000
1!
b00000000000000000000000010110011 %
1&
b00000000000000000000000010110011 *
b00000000000000000000000010110011 +
